avcloud/__init__.py
avcloud/experimental/__init__.py
avcloud/experimental/client.py
avcloud/experimental/http_client/__init__.py
avcloud/experimental/http_client/client.py
avcloud/experimental/lance_client/__init__.py
avcloud/experimental/lance_client/client.py
avcloud/experimental/oci/__init__.py
avcloud/experimental/oci/_logger.py
avcloud/experimental/oci/manager.py
avcloud/experimental/resources/downloader.py
avcloud/experimental/resources/downloader_v2.py
avcloud/experimental/resources/entity.py
avcloud/experimental/resources/search.py
avcloud/experimental/resources/search_v2.py
avcloud/experimental/resources/stats_collector.py
avcloud/experimental/schema_proto/README.md
avcloud/experimental/schema_proto/__init__.py
avcloud/experimental/schema_proto/av_data_schema.md
avcloud/experimental/schema_proto/av_schema.desc
avcloud/experimental/schema_proto/av_schema.proto
avcloud/experimental/schema_proto/av_schema_pb2.py
avcloud/experimental/schema_proto/av_schema_to_arrow.py
avcloud/experimental/schema_proto/build_registry.py
avcloud/experimental/schema_proto/calibration_msg.proto
avcloud/experimental/schema_proto/calibration_msg_pb2.py
avcloud/experimental/schema_proto/camera_msg.proto
avcloud/experimental/schema_proto/camera_msg_pb2.py
avcloud/experimental/schema_proto/geometry_msg.proto
avcloud/experimental/schema_proto/geometry_msg_pb2.py
avcloud/experimental/schema_proto/gnss_msg.proto
avcloud/experimental/schema_proto/gnss_msg_pb2.py
avcloud/experimental/schema_proto/imu_msg.proto
avcloud/experimental/schema_proto/imu_msg_pb2.py
avcloud/experimental/schema_proto/label_msg.proto
avcloud/experimental/schema_proto/label_msg_pb2.py
avcloud/experimental/schema_proto/lidar_msg.proto
avcloud/experimental/schema_proto/lidar_msg_pb2.py
avcloud/experimental/schema_proto/misc_data_msg.proto
avcloud/experimental/schema_proto/misc_data_msg_pb2.py
avcloud/experimental/schema_proto/pose_msg.proto
avcloud/experimental/schema_proto/pose_msg_pb2.py
avcloud-0.1.4.dist-info/METADATA
avcloud-0.1.4.dist-info/WHEEL
avcloud-0.1.4.dist-info/RECORD
