Metadata-Version: 2.4
Name: avcloud
Version: 0.1.4
Summary: repository to host external facing avcloud sdk
Author: Summer Li
Author-email: jiaoyli@umich.edu
Requires-Python: >=3.10
Classifier: Programming Language :: Python :: 3
Classifier: Programming Language :: Python :: 3.10
Classifier: Programming Language :: Python :: 3.11
Classifier: Programming Language :: Python :: 3.12
Classifier: Programming Language :: Python :: 3.13
Classifier: Programming Language :: Python :: 3.14
Requires-Dist: av (>=16.0.1,<17.0.0)
Requires-Dist: cryptography (>=46.0.3,<47.0.0)
Requires-Dist: httpx (>=0.28.1,<0.29.0)
Requires-Dist: mcap (>=1.3.0,<2.0.0)
Requires-Dist: opencv-python (>=4.12.0.88,<5.0.0.0)
Requires-Dist: pandas (>=2.0.0)
Requires-Dist: pillow (>=12.0.0,<13.0.0)
Requires-Dist: protobuf (>=6.31.0,<7.0.0)
Requires-Dist: pyarrow (>=17.0.0)
Requires-Dist: pydantic (>=2.0.0,<3.0.0)
Requires-Dist: pylance (==0.38.3)
Requires-Dist: python-jose (>=3.5.0,<4.0.0)
Requires-Dist: rosbags (>=0.11.0,<0.12.0)
Requires-Dist: scipy (>=1.11.0)
Requires-Dist: tomli (>=2.3.0,<3.0.0)
Requires-Dist: tqdm (>=4.66.0)
Requires-Dist: transforms3d (>=0.4.2,<0.5.0)
